turbolpc/__init__.py
turbolpc/analysis.py
turbolpc/synthesis.py
turbolpc/utils.py
turbolpc-1.0.0.dist-info/LICENSE
turbolpc-1.0.0.dist-info/METADATA
turbolpc-1.0.0.dist-info/WHEEL
turbolpc-1.0.0.dist-info/top_level.txt
turbolpc-1.0.0.dist-info/RECORD
