Metadata-Version: 2.1
Name: turbolpc
Version: 1.0.0
Summary: TurboLPC is a fast, simple yet powerful Python library that provides the functionality of Linear Predictive Coding for signals.
Home-page: https://github.com/MDFahimAnjum/TurboLPC
Author: Fahim Anjum
Author-email: dr.fahim.anjum@gmail.com
Classifier: Programming Language :: Python :: 3
Classifier: License :: OSI Approved :: MIT License
Classifier: Operating System :: OS Independent
Requires-Python: >=3.9
License-File: LICENSE
Requires-Dist: numpy ==1.26.4
Requires-Dist: scipy ==1.12.0
